eRCaGuy_PyColors/__init__.py
eRCaGuy_PyColors/__main__.py
eRCaGuy_PyColors/ansi_colors.py
ercaguy_pycolors-0.1.5.dist-info/licenses/LICENSE
ercaguy_pycolors-0.1.5.dist-info/METADATA
ercaguy_pycolors-0.1.5.dist-info/WHEEL
ercaguy_pycolors-0.1.5.dist-info/top_level.txt
ercaguy_pycolors-0.1.5.dist-info/RECORD
