Metadata-Version: 2.4
Name: eRCaGuy_PyColors
Version: 0.1.5
Summary: A Python module to add ANSI color and format codes to strings for terminal output
Author: Gabriel Staples
License-Expression: MIT
Project-URL: Homepage, https://gabrielstaples.com/
Project-URL: Issues, https://github.com/ElectricRCAircraftGuy/eRCaGuy_PyColors/issues
Project-URL: Repository, https://github.com/ElectricRCAircraftGuy/eRCaGuy_PyColors
Keywords: ansi,color,terminal,console,formatting,colorize,print,string
Classifier: Development Status :: 4 - Beta
Classifier: Intended Audience :: Developers
Classifier: Programming Language :: Python :: 3
Classifier: Programming Language :: Python :: 3.7
Classifier: Programming Language :: Python :: 3.8
Classifier: Programming Language :: Python :: 3.9
Classifier: Programming Language :: Python :: 3.10
Classifier: Programming Language :: Python :: 3.11
Classifier: Programming Language :: Python :: 3.12
Classifier: Topic :: Software Development :: Libraries :: Python Modules
Classifier: Topic :: Terminals
Requires-Python: >=3.7
License-File: LICENSE
Dynamic: license-file
